lazychains/__init__.py
lazychains/lazychains.py
lazychains-0.2.12.dist-info/LICENSE
lazychains-0.2.12.dist-info/METADATA
lazychains-0.2.12.dist-info/WHEEL
lazychains-0.2.12.dist-info/RECORD
