Metadata-Version: 2.1
Name: lazychains
Version: 0.2.12
Summary: Singly linked lists with incremental instantiation of iterators
Home-page: https://lazychains.readthedocs.io/en/latest/
License: GPL-3.0-or-later
Keywords: iterators,linked list,single,lazy
Author: Stephen Leach
Author-email: sfkleach@gmail.com
Requires-Python: >=3.10,<4.0
Classifier: Development Status :: 4 - Beta
Classifier: Intended Audience :: Developers
Classifier: License :: OSI Approved :: GNU Affero General Public License v3 or later (AGPLv3+)
Classifier: License :: OSI Approved :: GNU General Public License v3 or later (GPLv3+)
Classifier: Natural Language :: English
Classifier: Operating System :: OS Independent
Classifier: Programming Language :: Python :: 3
Classifier: Programming Language :: Python :: 3.10
Classifier: Programming Language :: Python :: 3.11
Classifier: Programming Language :: Python :: 3.12
Classifier: Topic :: Software Development :: Libraries
Classifier: Typing :: Typed
Project-URL: Documentation, https://lazychains.readthedocs.io/en/latest/
Project-URL: Repository, https://github.com/sfkleach/lazychains
